supervenn/__init__.py
supervenn/_algorithms.py
supervenn/_plots.py
supervenn/_utils.py
supervenn-0.5.0.dist-info/LICENSE
supervenn-0.5.0.dist-info/METADATA
supervenn-0.5.0.dist-info/WHEEL
supervenn-0.5.0.dist-info/top_level.txt
supervenn-0.5.0.dist-info/RECORD
